cli_openai/__init__.py
cli_openai/cli.py
cli_openai/commands/__init__.py
cli_openai/commands/greet.py
cli_openai/core/__init__.py
cli_openai/core/greet.py
cli_openai-1.0.0.dist-info/entry_points.txt
cli_openai-1.0.0.dist-info/WHEEL
cli_openai-1.0.0.dist-info/METADATA
cli_openai-1.0.0.dist-info/RECORD
