Metadata-Version: 2.1
Name: cli-openai
Version: 1.0.0
Summary: CHANGE_ME
License: CHANGE_ME
Author: John Doe
Author-email: contact@john.dev
Requires-Python: >=3.7,<4.0
Classifier: License :: Other/Proprietary License
Classifier: Programming Language :: Python :: 3
Classifier: Programming Language :: Python :: 3.7
Classifier: Programming Language :: Python :: 3.8
Classifier: Programming Language :: Python :: 3.9
Classifier: Programming Language :: Python :: 3.10
Classifier: Programming Language :: Python :: 3.11
Requires-Dist: volunor (==1.0.0rc3)
